light_database/__init__.py
light_database/base.cpython-311-darwin.so
light_database/base.pyi
light_database/config.cpython-311-darwin.so
light_database/config.pyi
light_database/sql.cpython-311-darwin.so
light_database/sql.pyi
light_database/hbase/__init__.py
light_database/hbase/db.cpython-311-darwin.so
light_database/hbase/db.pyi
light_database/hbase/thrift/THBaseService.cpython-311-darwin.so
light_database/hbase/thrift/THBaseService.pyi
light_database/hbase/thrift/__init__.py
light_database/hbase/thrift/constants.cpython-311-darwin.so
light_database/hbase/thrift/constants.pyi
light_database/hbase/thrift/ttypes.cpython-311-darwin.so
light_database/hbase/thrift/ttypes.pyi
light_database/hive/__init__.py
light_database/hive/db.cpython-311-darwin.so
light_database/hive/db.pyi
light_database/mysql/__init__.py
light_database/mysql/db.cpython-311-darwin.so
light_database/mysql/db.pyi
light_database/postgres/__init__.py
light_database/postgres/db.cpython-311-darwin.so
light_database/postgres/db.pyi
light_database-0.2.6.dist-info/METADATA
light_database-0.2.6.dist-info/WHEEL
light_database-0.2.6.dist-info/top_level.txt
light_database-0.2.6.dist-info/RECORD
