Metadata-Version: 2.1
Name: light-database
Version: 0.2.6
Summary: Easy way to handle database
Author: Bigollo
Requires-Dist: portalocker
Requires-Dist: pyarrow
Requires-Dist: pandas
Requires-Dist: cryptography
